setup.py
dsnd_probability_2020_0_1/Binomialdistribution.py
dsnd_probability_2020_0_1/Gaussiandistribution.py
dsnd_probability_2020_0_1/Generaldistribution.py
dsnd_probability_2020_0_1/__init__.py
dsnd_probability_2020_0_1.egg-info/PKG-INFO
dsnd_probability_2020_0_1.egg-info/SOURCES.txt
dsnd_probability_2020_0_1.egg-info/dependency_links.txt
dsnd_probability_2020_0_1.egg-info/not-zip-safe
dsnd_probability_2020_0_1.egg-info/top_level.txt