Metadata-Version: 1.0
Name: dsnd-probability-2020-0-1
Version: 1.0
Summary: Gaussian and Binomial distributions
Home-page: UNKNOWN
Author: Sharmin Ahmed
Author-email: UNKNOWN
License: UNKNOWN
Platform: UNKNOWN
